{
  "$schema": "https://turbo.build/schema.json",
  "tasks": {
    "dev": {
      "cache": false,
      "persistent": true
    },
    "build": {
      "dependsOn": [
        "^build"
      ],
      "outputs": [
        "dist/**",
        ".nuxt/**",
        ".output/**",
        "coverage/**"
      ]
    },
    "lint": {
      "dependsOn": [
        "^lint"
      ],
      "outputs": []
    },
    "test": {
      "dependsOn": [
        "^test"
      ],
      "outputs": [
        "coverage/**"
      ]
    },
    "typecheck": {
      "dependsOn": [
        "^typecheck"
      ],
      "outputs": []
    },
    "postinstall": {
      "cache": false
    }
  }
}
